<?xml version="1.0" encoding="UTF-8" standalone="no" ?>
<Application>

  <Header>
    <Version val="13000"/>
    <WithIsn val="Y"/>
    <_InternalTask val="N"/>
    <IsRoot val="N"/>
    <InIndex val="N"/>
  </Header>

  <ProgramsRepository>
    <Programs>
      <Task MainProgram="N">
        <Header Description="Főablak" ISN_2="1" LastIsn="1" id="6">
          <ExecutionRight comp="-1"/>
          <Resident val="N"/>
          <SQL val="N"/>
          <ReturnValue>
            <ReturnValueAttr MgAttr="N"/>
            <TSK_PARAMS val="1"/>
            <ParametersCount val="1"/>
            <ParametersAttributes>
              <Attr MgAttr="N"/>
            </ParametersAttributes>
          </ReturnValue>
          <SqlWhereExist val="N"/>
          <TaskType val="C"/>
          <Interactive val="Y"/>
          <External val="N"/>
          <Offline val="N"/>
          <FormType val="D"/>
          <DotNetObjectExists val="N"/>
          <LastModified _date="735935" _time="49644" date="03/12/2015" time="13:47:24"/>
        </Header>
        <ReturnValueExpression val="4"/>
        <ItemIsn val="6"/>
        <Resource>
          <DB>
            <DataObject comp="-1" obj="3"/>
            <Access val="W"/>
            <Share val="W"/>
            <Open val="N"/>
            <Cache val="Y"/>
            <IdentifyRowModifications val="84"/>
          </DB>
          <Columns>
            <Column id="3" name="pID">
              <PropertyList model="FIELD">
                <Model attr_obj="FIELD_NUMERIC" id="1"/>
                <Picture id="157" valUnicode="10"/>
                <_Dec id="181"/>
                <_Whole id="182" val="10"/>
                <_Negative id="192"/>
                <_FieldStyle id="276" val="1"/>
              </PropertyList>
            </Column>
          </Columns>
          <ColumnsLastIsn val="6"/>
        </Resource>
        <Information>
          <Key>
            <Column val="1"/>
            <Mode val="N"/>
          </Key>
          <DB comp="-1" obj="3"/>
          <Sort>
            <CLS val="A"/>
          </Sort>
          <ForceRecordDelete DEL="N"/>
          <EndTaskCondition val="N"/>
          <EvaluateEndCondition val="B"/>
          <InitialMode val="E"/>
          <Locate Direction="A"/>
          <Range Direction="A"/>
          <VarRange LastIsn="3"/>
          <TaskProperties>
            <SelectionTable val="N"/>
            <ConfirmUpdate CNFU="N"/>
            <ConfirmCancel val="N"/>
            <ErrorStrategy val="R"/>
            <LockingStrategy val="M"/>
            <CacheStrategy val="D"/>
            <ForceRecordSuffix val="N"/>
            <TransactionMode val="D"/>
            <TransactionBegin val="P"/>
            <PreloadView val="N"/>
            <AllowEmptyDataview val="Y"/>
            <KeepCreatedContext val="N"/>
          </TaskProperties>
          <SIDE_WIN>
            <AllowOptions val="N"/>
            <AllowQuery val="Y"/>
            <AllowModify val="Y"/>
            <AllowCreate val="N"/>
            <AllowDelete val="N"/>
            <AllowLocate val="Y"/>
            <AllowRange val="Y"/>
            <AllowIndexChange val="N"/>
            <AllowSorting val="Y"/>
            <AllowIOFiles val="N"/>
            <TabbingCycle val="R"/>
            <AllowEvents val="Y"/>
            <AllowIndexOptimization val="Y"/>
            <AllowLocationInQuery val="Y"/>
            <AllowPrintingData val="N"/>
          </SIDE_WIN>
          <WIN>
            <OpenTaskWindow val="Y"/>
            <CloseTaskWindow val="Y"/>
            <ForegroundWindow val="Y"/>
            <FlipFld val="N"/>
            <RefreshTaskWindow ReturnValue="N"/>
          </WIN>
          <BOX>
            <Direction val="V"/>
          </BOX>
        </Information>
        <INT_RECOMP_INFO>
          <v>2</v>
          <v>3</v>
          <v>0</v>
        </INT_RECOMP_INFO>
        <TaskLogic>
          <LogicUnit id="1" propagate="78">
            <Level val="R"/>
            <Type val="M"/>
            <_DspTemplate val="0"/>
            <_HeaderPosition val="1"/>
            <Scope val="S"/>
            <EngineDirective val="S"/>
            <ShowMessage val="Y"/>
            <Condition val="89"/>
            <_TotalVariabls val="4"/>
            <_TotalVirtuals val="1"/>
            <PRM_LEN val="1"/>
            <Event>
              <EventType val="S"/>
              <PublicObject comp="-1"/>
            </Event>
            <ExecuteOn_ val="O"/>
            <LogicLines>
              <LogicLine>
                <DATAVIEW_SRC FlowIsn="1" IDX="1" Type="M">
                  <Condition val="N"/>
                  <Modifier val="B"/>
                  <Direction val="C"/>
                </DATAVIEW_SRC>
              </LogicLine>
              <LogicLine>
                <Select FieldID="3" FlowIsn="8" id="3">
                  <Column val="1"/>
                  <Type val="V"/>
                  <IsParameter val="Y"/>
                  <_RecomputeIndex val="4"/>
                  <_FormIndex val="4"/>
                  <_ControlIndex val="4"/>
                  <_OleSubformIdx val="4"/>
                  <_TabbingOrderDspIndex val="4"/>
                  <DIFF_UPDATE val="T"/>
                  <Condition val="Y"/>
                  <Modifier val="S"/>
                  <Direction val="C"/>
                </Select>
              </LogicLine>
              <LogicLine>
                <Select FieldID="6" FlowIsn="15" id="6">
                  <Column val="1"/>
                  <Type val="R"/>
                  <IsParameter val="N"/>
                  <Range MAX="4" MIN="4"/>
                  <_RecomputeIndex val="4"/>
                  <_FormIndex val="4"/>
                  <_ControlIndex val="4"/>
                  <_OleSubformIdx val="4"/>
                  <_TabbingOrderDspIndex val="4"/>
                  <DIFF_UPDATE val="T"/>
                  <Condition val="Y"/>
                  <Modifier val="S"/>
                  <Direction val="C"/>
                </Select>
              </LogicLine>
              <LogicLine>
                <Select FieldID="4" FlowIsn="13" id="4">
                  <Column val="2"/>
                  <Type val="R"/>
                  <IsParameter val="N"/>
                  <_RecomputeIndex val="3"/>
                  <_FormIndex val="3"/>
                  <_ControlLength val="1"/>
                  <_ControlIndex val="3"/>
                  <_OleSubformIdx val="3"/>
                  <_TabbingOrderDspIndex val="3"/>
                  <DIFF_UPDATE val="T"/>
                  <Condition val="Y"/>
                  <Modifier val="S"/>
                  <Direction val="C"/>
                </Select>
              </LogicLine>
              <LogicLine>
                <Select FieldID="5" FlowIsn="14" id="5">
                  <Column val="4"/>
                  <Type val="R"/>
                  <IsParameter val="N"/>
                  <_RecomputeIndex val="1"/>
                  <_FormIndex val="1"/>
                  <_ControlLength val="2"/>
                  <_ControlIndex val="1"/>
                  <_OleSubformIdx val="1"/>
                  <_TabbingOrderDspIndex val="1"/>
                  <DIFF_UPDATE val="T"/>
                  <Condition val="Y"/>
                  <Modifier val="S"/>
                  <Direction val="C"/>
                </Select>
              </LogicLine>
            </LogicLines>
          </LogicUnit>
          <LogicUnit id="3" propagate="78">
            <Level val="H"/>
            <Type val="U"/>
            <_DspTemplate val="0"/>
            <_HeaderPosition val="4"/>
            <Scope val="S"/>
            <EngineDirective val="S"/>
            <ShowMessage val="Y"/>
            <Condition val="89"/>
            <Event>
              <EventType val="U"/>
              <PublicObject comp="-1" obj="1"/>
            </Event>
            <Expanded val="1"/>
            <ExecuteOn_ val="O"/>
            <LogicLines>
              <LogicLine>
                <Update FlowIsn="6">
                  <FieldID val="3"/>
                  <WithValue val="2"/>
                  <Incremental val="N"/>
                  <ForcedUpdate val="Y"/>
                  <Condition val="Y"/>
                  <Modifier val="B"/>
                  <Direction val="C"/>
                </Update>
              </LogicLine>
              <LogicLine>
                <RaiseEvent FlowIsn="7">
                  <Event>
                    <EventType val="I"/>
                    <InternalEventID val="14"/>
                    <PublicObject comp="-1"/>
                  </Event>
                  <Wait val="78"/>
                  <Condition val="Y"/>
                  <Modifier val="B"/>
                  <Direction val="C"/>
                </RaiseEvent>
              </LogicLine>
            </LogicLines>
          </LogicUnit>
          <LogicUnit id="4" propagate="78">
            <Level val="H"/>
            <Type val="U"/>
            <_DspTemplate val="0"/>
            <_HeaderPosition val="8"/>
            <Scope val="S"/>
            <EngineDirective val="S"/>
            <ShowMessage val="Y"/>
            <Condition val="89"/>
            <Event>
              <EventType val="I"/>
              <InternalEventID val="13"/>
              <PublicObject comp="-1"/>
            </Event>
            <Expanded val="1"/>
            <ExecuteOn_ val="O"/>
            <LogicLines>
              <LogicLine>
                <Update FlowIsn="20">
                  <FieldID val="3"/>
                  <WithValue val="3"/>
                  <Incremental val="N"/>
                  <ForcedUpdate val="Y"/>
                  <Condition val="Y"/>
                  <Modifier val="B"/>
                  <Direction val="C"/>
                </Update>
              </LogicLine>
            </LogicLines>
          </LogicUnit>
          <LogicUnit id="5" propagate="78">
            <Level val="H"/>
            <Type val="U"/>
            <_DspTemplate val="-1"/>
            <_HeaderPosition val="9"/>
            <Scope val="T"/>
            <EngineDirective val="S"/>
            <ShowMessage val="Y"/>
            <Condition val="89"/>
            <Event>
              <EventType val="U"/>
              <PublicObject comp="-1" obj="3"/>
            </Event>
            <TXT val="Jegyek nyomtatása"/>
            <Expanded val="1"/>
            <ExecuteOn_ val="O"/>
            <LogicLines>
              <LogicLine>
                <CallTask FlowIsn="22">
                  <OperationType val="P"/>
                  <TaskID comp="-1" obj="10"/>
                  <Lock val="N"/>
                  <Arguments>
                    <Argument>
                      <id val="1"/>
                      <Variable val="1"/>
                      <Skip val="N"/>
                    </Argument>
                  </Arguments>
                  <Wait val="Y"/>
                  <SyncData val="N"/>
                  <RetainFocus val="N"/>
                  <Condition val="Y"/>
                  <Modifier val="B"/>
                  <Direction val="C"/>
                </CallTask>
              </LogicLine>
            </LogicLines>
          </LogicUnit>
        </TaskLogic>
        <TaskForms>
          <FormEntry _last_isn="4" _last_test_id="4" id="1">
            <PropertyList model="FORM_RICH_CLIENT">
              <Model comp="-1" id="1" obj="2"/>
              <Width id="23" val="745"/>
              <Height id="24" val="479"/>
              <_Comment id="218"/>
              <FormName id="311" valUnicode="Főablak"/>
            </PropertyList>
            <Control _test_id="2" id="2">
              <PropertyList model="CTRL_RICH_CLIENT_LABEL">
                <Text Exp="1" id="19" valUnicode="Text"/>
                <X id="21" val="513"/>
                <Y id="22" val="21"/>
                <Width id="23" val="115"/>
                <Height id="24" val="16"/>
                <_Orientation id="143"/>
              </PropertyList>
            </Control>
            <Control PDOD="128" _test_id="1" id="1">
              <PropertyList model="CTRL_RICH_CLIENT_PUSH_BUTTON">
                <X id="21" val="650"/>
                <Y id="22" val="14"/>
                <Width id="23" val="70"/>
                <Height id="24" val="23"/>
                <Format id="82" valUnicode="Kijelentkezés"/>
                <RaiseEvent id="234">
                  <EventType val="U"/>
                  <PublicObject comp="-1" obj="1"/>
                </RaiseEvent>
                <TabOrder id="314" val="1"/>
              </PropertyList>
            </Control>
            <Control PDOD="128" _test_id="3" id="3">
              <PropertyList model="CTRL_RICH_CLIENT_SUBFORM">
                <X id="21" val="40"/>
                <Y id="22" val="75"/>
                <Width id="23" val="553"/>
                <Height id="24" val="358"/>
                <TaskNumber Exp="5" id="183"/>
                <AutoFit id="313" val="3"/>
                <TabOrder id="314" val="2"/>
              </PropertyList>
            </Control>
            <Control PDOD="128" _test_id="4" id="4">
              <PropertyList model="CTRL_RICH_CLIENT_PUSH_BUTTON">
                <X id="21" val="609"/>
                <Y id="22" val="91"/>
                <Width id="23" val="111"/>
                <Height id="24" val="47"/>
                <ControlName id="46" val="Jegyek nyomtatása"/>
                <Visible Exp="6" id="61"/>
                <Format id="82" valUnicode="Jegyek nyomtatása"/>
                <RaiseEvent id="234">
                  <EventType val="U"/>
                  <PublicObject comp="-1" obj="3"/>
                </RaiseEvent>
                <TabOrder id="314" val="3"/>
              </PropertyList>
            </Control>
          </FormEntry>
        </TaskForms>
        <Expressions>
          <Expression id="1">
            <ExpSyntax val="'Belépve: '&amp;{0,4}"/>
            <ExpAttribute val="A"/>
          </Expression>
          <Expression id="2">
            <ExpSyntax val="0"/>
            <ExpAttribute val="N"/>
          </Expression>
          <Expression id="3">
            <ExpSyntax val="-1"/>
            <ExpAttribute val="N"/>
          </Expression>
          <Expression id="4">
            <ExpSyntax val="{0,3}"/>
            <ExpAttribute val="N"/>
          </Expression>
          <Expression id="5">
            <ExpSyntax val="IF({0,5}=1,'{8,-1}'PROG,'{9,-1}'PROG)"/>
            <ExpAttribute val="N"/>
          </Expression>
          <Expression id="6">
            <ExpSyntax val="{0,5}=2"/>
            <ExpAttribute val="B"/>
          </Expression>
        </Expressions>
        <EVNT DESC="Kilepes" FORCE_EXIT="N" id="1">
          <Event>
            <EventType val="N"/>
            <PublicObject comp="-1"/>
          </Event>
        </EVNT>
        <EVNT DESC="Jegyek nyomtatása" FORCE_EXIT="N" id="3">
          <Event>
            <EventType val="S"/>
            <PublicObject comp="-1"/>
          </Event>
        </EVNT>
        <VarRangeInfo Mode="E" VarRangeVeeIsn="6" id="1"/>
      </Task>
    </Programs>
  </ProgramsRepository>

</Application>
